lzip_extension.cpython-310-x86_64-linux-gnu.so
lzip.libs/libgcc_s-a04fdf82.so.1
lzip.libs/libstdc++-a9383cce.so.6.0.28
lzip-1.2.0.dist-info/top_level.txt
lzip-1.2.0.dist-info/METADATA
lzip-1.2.0.dist-info/LICENSE
lzip-1.2.0.dist-info/RECORD
lzip-1.2.0.dist-info/WHEEL
lzip/version.py
lzip/__init__.py
lzip/lzip.py
