Metadata-Version: 2.1
Name: lzip
Version: 1.2.0
Summary: Lzip (.lz) archives compression and decompression with buffers and URLs support
Home-page: https://github.com/neuromorphicsystems/lzip
Author: Alexandre Marcireau
Author-email: alexandre.marcireau@gmail.com
License: UNKNOWN
Platform: UNKNOWN
Classifier: Programming Language :: Python :: 3
Classifier: License :: OSI Approved :: GNU General Public License v3 (GPLv3)
Classifier: Operating System :: OS Independent
License-File: LICENSE
